raiden_api_client/__init__.py
raiden_api_client/exceptions.py
raiden_api_client/wrapper.py
raiden_api_client-1.1.1.dist-info/AUTHORS.rst
raiden_api_client-1.1.1.dist-info/LICENSE.txt
raiden_api_client-1.1.1.dist-info/METADATA
raiden_api_client-1.1.1.dist-info/WHEEL
raiden_api_client-1.1.1.dist-info/top_level.txt
raiden_api_client-1.1.1.dist-info/zip-safe
raiden_api_client-1.1.1.dist-info/RECORD
