Metadata-Version: 2.1
Name: raiden-api-client
Version: 1.1.1
Summary: Python wrapper for the Raiden Network node API
Home-page: https://github.com/raiden-network/raiden-api-client
Author: Maximilian Langenfeld, Oliver Bünting
Author-email: maxdacjs@gmail.com
License: mit
Platform: any
Classifier: Development Status :: 4 - Beta
Classifier: Programming Language :: Python
Requires-Dist: requests
Requires-Dist: attrdict
Provides-Extra: testing
Requires-Dist: pytest ; extra == 'testing'
Requires-Dist: pytest-cov ; extra == 'testing'
